yms_class/__init__.py
yms_class/version.py
yms_class/models/AlexNet.py
yms_class/models/CNN.py
yms_class/models/DECAE.py
yms_class/models/KKAN.py
yms_class/models/OrdinalRegression.py
yms_class/models/__init__.py
yms_class/models/autoencoder.py
yms_class/run/FeatureExtraction.py
yms_class/run/__init__.py
yms_class/run/predict.py
yms_class/run/train.py
yms_class/run/train_decoder.py
yms_class/run/train_ord.py
yms_class/run/validation.py
yms_class/src/__init__.py
yms_class/src/convolution/KANLayer.py
yms_class/src/convolution/__init__.py
yms_class/src/convolution/cov.py
yms_class/src/convolution/spline.py
yms_class/src/convolution/utils.py
yms_class/src/efficient_kan/__init__.py
yms_class/src/efficient_kan/kan.py
yms_class/src/kan_convolutional/KANConv.py
yms_class/src/kan_convolutional/KANLinear.py
yms_class/src/kan_convolutional/__init__.py
yms_class/src/kan_convolutional/convolution.py
yms_class/tools/__init__.py
yms_class/tools/cwt.py
yms_class/tools/data_split.py
yms_class/tools/dataset.py
yms_class/tools/kaggle.py
yms_class/tools/photos.py
yms_class/tools/plotting.py
yms_class/tools/tool.py
yms_class/tools/train_eval_utils.py
yms_class-0.1.4.dist-info/licenses/LICENSE
yms_class-0.1.4.dist-info/METADATA
yms_class-0.1.4.dist-info/WHEEL
yms_class-0.1.4.dist-info/top_level.txt
yms_class-0.1.4.dist-info/RECORD
